{
  "openapi": "3.0.1",
  "info": {
    "title": "HaatBazar",
    "version": "1.0"
  },
  "paths": {
    "/api/Category/getAllCategory": {
      "get": {
        "tags": [
          "Category"
        ],
        "responses": {
          "200": {
            "description": "OK"
          }
        }
      }
    },
    "/api/Category/saveCategory": {
      "post": {
        "tags": [
          "Category"
        ],
        "requestBody": {
          "content": {
            "application/json": {
              "schema": {
                "$ref": "#/components/schemas/CategoryMaster"
              }
            },
            "text/json": {
              "schema": {
                "$ref": "#/components/schemas/CategoryMaster"
              }
            },
            "application/*+json": {
              "schema": {
                "$ref": "#/components/schemas/CategoryMaster"
              }
            }
          }
        },
        "responses": {
          "200": {
            "description": "OK"
          }
        }
      }
    },
    "/api/Category/updateCategory": {
      "put": {
        "tags": [
          "Category"
        ],
        "requestBody": {
          "content": {
            "application/json": {
              "schema": {
                "$ref": "#/components/schemas/CategoryMaster"
              }
            },
            "text/json": {
              "schema": {
                "$ref": "#/components/schemas/CategoryMaster"
              }
            },
            "application/*+json": {
              "schema": {
                "$ref": "#/components/schemas/CategoryMaster"
              }
            }
          }
        },
        "responses": {
          "200": {
            "description": "OK"
          }
        }
      }
    },
    "/api/Category": {
      "delete": {
        "tags": [
          "Category"
        ],
        "parameters": [
          {
            "name": "id",
            "in": "query",
            "schema": {
              "type": "integer",
              "format": "int32"
            }
          }
        ],
        "responses": {
          "200": {
            "description": "OK"
          }
        }
      }
    },
    "/api/ChildCategory/list-with-category": {
      "get": {
        "tags": [
          "ChildCategory"
        ],
        "responses": {
          "200": {
            "description": "OK"
          }
        }
      }
    },
    "/api/ChildCategory/saveChildCategory": {
      "post": {
        "tags": [
          "ChildCategory"
        ],
        "requestBody": {
          "content": {
            "application/json": {
              "schema": {
                "$ref": "#/components/schemas/ChildCategoryMaster"
              }
            },
            "text/json": {
              "schema": {
                "$ref": "#/components/schemas/ChildCategoryMaster"
              }
            },
            "application/*+json": {
              "schema": {
                "$ref": "#/components/schemas/ChildCategoryMaster"
              }
            }
          }
        },
        "responses": {
          "200": {
            "description": "OK"
          }
        }
      }
    },
    "/api/ChildCategory/updateChildCategory": {
      "put": {
        "tags": [
          "ChildCategory"
        ],
        "requestBody": {
          "content": {
            "application/json": {
              "schema": {
                "$ref": "#/components/schemas/ChildCategoryMaster"
              }
            },
            "text/json": {
              "schema": {
                "$ref": "#/components/schemas/ChildCategoryMaster"
              }
            },
            "application/*+json": {
              "schema": {
                "$ref": "#/components/schemas/ChildCategoryMaster"
              }
            }
          }
        },
        "responses": {
          "200": {
            "description": "OK"
          }
        }
      }
    },
    "/api/ChildCategory/deleteChildCategory": {
      "delete": {
        "tags": [
          "ChildCategory"
        ],
        "parameters": [
          {
            "name": "id",
            "in": "query",
            "schema": {
              "type": "integer",
              "format": "int32"
            }
          }
        ],
        "responses": {
          "200": {
            "description": "OK"
          }
        }
      }
    },
    "/WeatherForecast": {
      "get": {
        "tags": [
          "WeatherForecast"
        ],
        "operationId": "GetWeatherForecast",
        "responses": {
          "200": {
            "description": "OK",
            "content": {
              "text/plain": {
                "schema": {
                  "type": "array",
                  "items": {
                    "$ref": "#/components/schemas/WeatherForecast"
                  }
                }
              },
              "application/json": {
                "schema": {
                  "type": "array",
                  "items": {
                    "$ref": "#/components/schemas/WeatherForecast"
                  }
                }
              },
              "text/json": {
                "schema": {
                  "type": "array",
                  "items": {
                    "$ref": "#/components/schemas/WeatherForecast"
                  }
                }
              }
            }
          }
        }
      }
    }
  },
  "components": {
    "schemas": {
      "CategoryMaster": {
        "required": [
          "categoryName",
          "imageName"
        ],
        "type": "object",
        "properties": {
          "categoryId": {
            "type": "integer",
            "format": "int32"
          },
          "categoryName": {
            "maxLength": 100,
            "minLength": 0,
            "type": "string"
          },
          "imageName": {
            "maxLength": 100,
            "minLength": 0,
            "type": "string"
          }
        },
        "additionalProperties": false
      },
      "ChildCategoryMaster": {
        "required": [
          "categoryId",
          "childCategoryName"
        ],
        "type": "object",
        "properties": {
          "childCategoryId": {
            "type": "integer",
            "format": "int32"
          },
          "categoryId": {
            "type": "integer",
            "format": "int32"
          },
          "childCategoryName": {
            "maxLength": 100,
            "minLength": 0,
            "type": "string"
          }
        },
        "additionalProperties": false
      },
      "WeatherForecast": {
        "type": "object",
        "properties": {
          "date": {
            "type": "string",
            "format": "date"
          },
          "temperatureC": {
            "type": "integer",
            "format": "int32"
          },
          "temperatureF": {
            "type": "integer",
            "format": "int32",
            "readOnly": true
          },
          "summary": {
            "type": "string",
            "nullable": true
          }
        },
        "additionalProperties": false
      }
    }
  }
}